setup.cfg
setup.py
bin/mexec
mexec/__init__.py
mexec/docker.py
mexec/mesos.py
mexec.egg-info/PKG-INFO
mexec.egg-info/SOURCES.txt
mexec.egg-info/dependency_links.txt
mexec.egg-info/not-zip-safe
mexec.egg-info/pbr.json
mexec.egg-info/requires.txt
mexec.egg-info/top_level.txt