Metadata-Version: 1.0
Name: mexec
Version: 0.1.0
Summary: Execute commands inside docker containers run by mesos
Home-page: http://github.com/tdna/mexec
Author: Andras Toth
Author-email: ta1986@gmail.com
License: BSD
Keywords: mesos docker
Platform: UNKNOWN
